jsondoc/__init__.py
jsondoc/rules.py
jsondoc/serialize.py
jsondoc/bin/convert_jsondoc.py
jsondoc/bin/validate_jsondoc.py
jsondoc/convert/__init__.py
jsondoc/convert/html.py
jsondoc/convert/markdown.py
jsondoc/convert/placeholder.py
jsondoc/convert/utils.py
jsondoc/models/__init__.py
jsondoc/models/block/__init__.py
jsondoc/models/block/base/__init__.py
jsondoc/models/block/types/__init__.py
jsondoc/models/block/types/bulleted_list_item/__init__.py
jsondoc/models/block/types/code/__init__.py
jsondoc/models/block/types/column/__init__.py
jsondoc/models/block/types/column_list/__init__.py
jsondoc/models/block/types/divider/__init__.py
jsondoc/models/block/types/equation/__init__.py
jsondoc/models/block/types/heading_1/__init__.py
jsondoc/models/block/types/heading_2/__init__.py
jsondoc/models/block/types/heading_3/__init__.py
jsondoc/models/block/types/image/__init__.py
jsondoc/models/block/types/image/external_image/__init__.py
jsondoc/models/block/types/image/file_image/__init__.py
jsondoc/models/block/types/numbered_list_item/__init__.py
jsondoc/models/block/types/paragraph/__init__.py
jsondoc/models/block/types/quote/__init__.py
jsondoc/models/block/types/rich_text/__init__.py
jsondoc/models/block/types/rich_text/base/__init__.py
jsondoc/models/block/types/rich_text/equation/__init__.py
jsondoc/models/block/types/rich_text/text/__init__.py
jsondoc/models/block/types/table/__init__.py
jsondoc/models/block/types/table_row/__init__.py
jsondoc/models/block/types/to_do/__init__.py
jsondoc/models/block/types/toggle/__init__.py
jsondoc/models/file/__init__.py
jsondoc/models/file/base/__init__.py
jsondoc/models/file/external/__init__.py
jsondoc/models/file/file/__init__.py
jsondoc/models/page/__init__.py
jsondoc/models/shared_definitions/__init__.py
jsondoc/utils/__init__.py
jsondoc/utils/block.py
jsondoc/utils/text_with_backref.py
jsondoc/validate/__init__.py
python_jsondoc-0.1.0.post6.dist-info/METADATA
python_jsondoc-0.1.0.post6.dist-info/WHEEL
python_jsondoc-0.1.0.post6.dist-info/entry_points.txt
python_jsondoc-0.1.0.post6.dist-info/RECORD
